imu_python/__init__.py
imu_python/__main__.py
imu_python/base_classes.py
imu_python/definitions.py
imu_python/devices.py
imu_python/factory.py
imu_python/i2c_bus.py
imu_python/orientation_filter.py
imu_python/sensor_manager.py
imu_python/utils.py
imu_python/wrapper.py
imu_python/data_handler/__init__.py
imu_python/data_handler/data_plotter.py
imu_python/data_handler/data_reader.py
imu_python/data_handler/data_writer.py
imu_python/data_handler/gain_calculator.py
imu_python-0.0.12.dist-info/METADATA
imu_python-0.0.12.dist-info/WHEEL
imu_python-0.0.12.dist-info/licenses/LICENSE
imu_python-0.0.12.dist-info/RECORD
