Metadata-Version: 2.4
Name: imu_python
Version: 0.0.12
Summary: IMU sensor codes in Python for the exosuit
Project-URL: homepage, https://github.com/TUM-Aries-Lab/imu-module
Author-email: Tsmorz <tony.smoragiewicz@tum.de>, CatYang3 <haoqing.yang@tum.de>
License-File: LICENSE
Requires-Python: <3.14,>=3.11
Requires-Dist: ahrs>=0.4.0
Requires-Dist: loguru>=0.7.3
Requires-Dist: matplotlib>=3.10.8
Requires-Dist: numpy>=2.2.3
Requires-Dist: pandas>=2.3.3
Requires-Dist: scipy>=1.16.3
Provides-Extra: dev
Requires-Dist: coveralls>=4.0.1; extra == 'dev'
Requires-Dist: pre-commit>=4.1.0; extra == 'dev'
Requires-Dist: pyright>=1.1.407; extra == 'dev'
Requires-Dist: pytest-cov>=6.0; extra == 'dev'
Requires-Dist: pytest>=8.3; extra == 'dev'
Requires-Dist: ruff>=0.6.9; extra == 'dev'
Provides-Extra: hw
Requires-Dist: adafruit-circuitpython-bno055>=5.4.20; extra == 'hw'
Requires-Dist: adafruit-circuitpython-bno08x>=1.3.1; extra == 'hw'
Requires-Dist: adafruit-circuitpython-lis3mdl>=1.2.6; extra == 'hw'
Requires-Dist: adafruit-circuitpython-lsm6ds>=4.5.18; extra == 'hw'
Requires-Dist: adafruit-extended-bus>=1.0.2; extra == 'hw'
Requires-Dist: jetson-gpio>=2.1.12; extra == 'hw'
Provides-Extra: no-hw
